[
    {
        "id": "vpn508531084.opengw.net:995",
        "name": "South Korea 1727",
        "country": "South Korea",
        "host": "vpn508531084.opengw.net",
        "port": 995,
        "username": "vpn",
        "password": "vpn",
        "is_new": true
    },
    {
        "id": "vpn981288372.opengw.net:1925",
        "name": "Japan 1657",
        "country": "Japan",
        "host": "vpn981288372.opengw.net",
        "port": 1925,
        "username": "vpn",
        "password": "vpn",
        "is_new": true
    },
    {
        "id": "vpn257046363.opengw.net:1936",
        "name": "South Korea 1728",
        "country": "South Korea",
        "host": "vpn257046363.opengw.net",
        "port": 1936,
        "username": "vpn",
        "password": "vpn",
        "is_new": true
    },
    {
        "id": "vpn686914656.opengw.net:1307",
        "name": "Japan 1658",
        "country": "Japan",
        "host": "vpn686914656.opengw.net",
        "port": 1307,
        "username": "vpn",
        "password": "vpn",
        "is_new": true
    },
    {
        "id": "vpn928731604.opengw.net:1681",
        "name": "South Korea 1729",
        "country": "South Korea",
        "host": "vpn928731604.opengw.net",
        "port": 1681,
        "username": "vpn",
        "password": "vpn",
        "is_new": true
    },
    {
        "id": "vpn513832073.opengw.net:1646",
        "name": "Thailand 84",
        "country": "Thailand",
        "host": "vpn513832073.opengw.net",
        "port": 1646,
        "username": "vpn",
        "password": "vpn",
        "is_new": true
    },
    {
        "id": "vpn857907455.opengw.net:1787",
        "name": "Thailand 85",
        "country": "Thailand",
        "host": "vpn857907455.opengw.net",
        "port": 1787,
        "username": "vpn",
        "password": "vpn",
        "is_new": true
    },
    {
        "id": "vpn527637649.opengw.net:1972",
        "name": "Japan 1659",
        "country": "Japan",
        "host": "vpn527637649.opengw.net",
        "port": 1972,
        "username": "vpn",
        "password": "vpn",
        "is_new": true
    },
    {
        "id": "vpn199508608.opengw.net:1291",
        "name": "South Korea 1730",
        "country": "South Korea",
        "host": "vpn199508608.opengw.net",
        "port": 1291,
        "username": "vpn",
        "password": "vpn",
        "is_new": true
    }
]