[
    {
        "id": "vpn711804982.opengw.net:1285",
        "name": "Russia 193",
        "country": "Russia",
        "host": "vpn711804982.opengw.net",
        "port": 1285,
        "username": "vpn",
        "password": "vpn",
        "is_new": true
    },
    {
        "id": "vpn583815286.opengw.net:1703",
        "name": "South Korea 906",
        "country": "South Korea",
        "host": "vpn583815286.opengw.net",
        "port": 1703,
        "username": "vpn",
        "password": "vpn",
        "is_new": true
    },
    {
        "id": "vpn931771153.opengw.net:1237",
        "name": "Japan 930",
        "country": "Japan",
        "host": "vpn931771153.opengw.net",
        "port": 1237,
        "username": "vpn",
        "password": "vpn",
        "is_new": true
    },
    {
        "id": "vpn722828815.opengw.net:1606",
        "name": "Japan 931",
        "country": "Japan",
        "host": "vpn722828815.opengw.net",
        "port": 1606,
        "username": "vpn",
        "password": "vpn",
        "is_new": true
    },
    {
        "id": "vpn594885882.opengw.net:995",
        "name": "South Korea 907",
        "country": "South Korea",
        "host": "vpn594885882.opengw.net",
        "port": 995,
        "username": "vpn",
        "password": "vpn",
        "is_new": true
    },
    {
        "id": "vpn983949836.opengw.net:1402",
        "name": "Japan 932",
        "country": "Japan",
        "host": "vpn983949836.opengw.net",
        "port": 1402,
        "username": "vpn",
        "password": "vpn",
        "is_new": true
    },
    {
        "id": "vpn211682518.opengw.net:995",
        "name": "Russia 194",
        "country": "Russia",
        "host": "vpn211682518.opengw.net",
        "port": 995,
        "username": "vpn",
        "password": "vpn",
        "is_new": true
    },
    {
        "id": "vpn996376689.opengw.net:995",
        "name": "South Korea 908",
        "country": "South Korea",
        "host": "vpn996376689.opengw.net",
        "port": 995,
        "username": "vpn",
        "password": "vpn",
        "is_new": true
    },
    {
        "id": "vpn524647489.opengw.net:1902",
        "name": "United States 76",
        "country": "United States",
        "host": "vpn524647489.opengw.net",
        "port": 1902,
        "username": "vpn",
        "password": "vpn",
        "is_new": true
    },
    {
        "id": "vpn809831957.opengw.net:1442",
        "name": "Japan 933",
        "country": "Japan",
        "host": "vpn809831957.opengw.net",
        "port": 1442,
        "username": "vpn",
        "password": "vpn",
        "is_new": true
    },
    {
        "id": "vpn818720720.opengw.net:1944",
        "name": "Japan 934",
        "country": "Japan",
        "host": "vpn818720720.opengw.net",
        "port": 1944,
        "username": "vpn",
        "password": "vpn",
        "is_new": true
    },
    {
        "id": "vpn613548820.opengw.net:1467",
        "name": "Japan 935",
        "country": "Japan",
        "host": "vpn613548820.opengw.net",
        "port": 1467,
        "username": "vpn",
        "password": "vpn",
        "is_new": true
    },
    {
        "id": "vpn156555613.opengw.net:1386",
        "name": "Japan 936",
        "country": "Japan",
        "host": "vpn156555613.opengw.net",
        "port": 1386,
        "username": "vpn",
        "password": "vpn",
        "is_new": true
    },
    {
        "id": "vpn756512970.opengw.net:1960",
        "name": "South Korea 909",
        "country": "South Korea",
        "host": "vpn756512970.opengw.net",
        "port": 1960,
        "username": "vpn",
        "password": "vpn",
        "is_new": true
    },
    {
        "id": "vpn642726083.opengw.net:1267",
        "name": "Japan 937",
        "country": "Japan",
        "host": "vpn642726083.opengw.net",
        "port": 1267,
        "username": "vpn",
        "password": "vpn",
        "is_new": true
    },
    {
        "id": "vpn420157597.opengw.net:1977",
        "name": "Thailand 51",
        "country": "Thailand",
        "host": "vpn420157597.opengw.net",
        "port": 1977,
        "username": "vpn",
        "password": "vpn",
        "is_new": true
    },
    {
        "id": "vpn778887611.opengw.net:1234",
        "name": "Japan 938",
        "country": "Japan",
        "host": "vpn778887611.opengw.net",
        "port": 1234,
        "username": "vpn",
        "password": "vpn",
        "is_new": true
    },
    {
        "id": "vpn604585457.opengw.net:1812",
        "name": "Japan 939",
        "country": "Japan",
        "host": "vpn604585457.opengw.net",
        "port": 1812,
        "username": "vpn",
        "password": "vpn",
        "is_new": true
    },
    {
        "id": "vpn967949276.opengw.net:995",
        "name": "South Korea 910",
        "country": "South Korea",
        "host": "vpn967949276.opengw.net",
        "port": 995,
        "username": "vpn",
        "password": "vpn",
        "is_new": true
    },
    {
        "id": "vpn916638706.opengw.net:995",
        "name": "South Korea 911",
        "country": "South Korea",
        "host": "vpn916638706.opengw.net",
        "port": 995,
        "username": "vpn",
        "password": "vpn",
        "is_new": true
    },
    {
        "id": "vpn718769017.opengw.net:995",
        "name": "South Korea 912",
        "country": "South Korea",
        "host": "vpn718769017.opengw.net",
        "port": 995,
        "username": "vpn",
        "password": "vpn",
        "is_new": true
    },
    {
        "id": "vpn485139505.opengw.net:1609",
        "name": "South Korea 913",
        "country": "South Korea",
        "host": "vpn485139505.opengw.net",
        "port": 1609,
        "username": "vpn",
        "password": "vpn",
        "is_new": true
    },
    {
        "id": "vpn548022105.opengw.net:1770",
        "name": "South Korea 914",
        "country": "South Korea",
        "host": "vpn548022105.opengw.net",
        "port": 1770,
        "username": "vpn",
        "password": "vpn",
        "is_new": true
    },
    {
        "id": "vpn301583961.opengw.net:995",
        "name": "South Korea 915",
        "country": "South Korea",
        "host": "vpn301583961.opengw.net",
        "port": 995,
        "username": "vpn",
        "password": "vpn",
        "is_new": true
    },
    {
        "id": "vpn362982314.opengw.net:995",
        "name": "South Korea 916",
        "country": "South Korea",
        "host": "vpn362982314.opengw.net",
        "port": 995,
        "username": "vpn",
        "password": "vpn",
        "is_new": true
    },
    {
        "id": "vpn307948504.opengw.net:995",
        "name": "South Korea 917",
        "country": "South Korea",
        "host": "vpn307948504.opengw.net",
        "port": 995,
        "username": "vpn",
        "password": "vpn",
        "is_new": true
    },
    {
        "id": "vpn866182768.opengw.net:995",
        "name": "South Korea 918",
        "country": "South Korea",
        "host": "vpn866182768.opengw.net",
        "port": 995,
        "username": "vpn",
        "password": "vpn",
        "is_new": true
    },
    {
        "id": "vpn909944744.opengw.net:1837",
        "name": "South Korea 919",
        "country": "South Korea",
        "host": "vpn909944744.opengw.net",
        "port": 1837,
        "username": "vpn",
        "password": "vpn",
        "is_new": true
    },
    {
        "id": "vpn940577737.opengw.net:995",
        "name": "South Korea 920",
        "country": "South Korea",
        "host": "vpn940577737.opengw.net",
        "port": 995,
        "username": "vpn",
        "password": "vpn",
        "is_new": true
    },
    {
        "id": "vpn353169637.opengw.net:1313",
        "name": "Russia 195",
        "country": "Russia",
        "host": "vpn353169637.opengw.net",
        "port": 1313,
        "username": "vpn",
        "password": "vpn",
        "is_new": true
    },
    {
        "id": "vpn546158955.opengw.net:1484",
        "name": "Japan 940",
        "country": "Japan",
        "host": "vpn546158955.opengw.net",
        "port": 1484,
        "username": "vpn",
        "password": "vpn",
        "is_new": true
    },
    {
        "id": "vpn944629289.opengw.net:1252",
        "name": "Russia 196",
        "country": "Russia",
        "host": "vpn944629289.opengw.net",
        "port": 1252,
        "username": "vpn",
        "password": "vpn",
        "is_new": true
    },
    {
        "id": "vpn158443453.opengw.net:1555",
        "name": "Russia 197",
        "country": "Russia",
        "host": "vpn158443453.opengw.net",
        "port": 1555,
        "username": "vpn",
        "password": "vpn",
        "is_new": true
    },
    {
        "id": "vpn366408079.opengw.net:1971",
        "name": "Indonesia 10",
        "country": "Indonesia",
        "host": "vpn366408079.opengw.net",
        "port": 1971,
        "username": "vpn",
        "password": "vpn",
        "is_new": true
    },
    {
        "id": "vpn851811740.opengw.net:995",
        "name": "South Korea 671",
        "country": "South Korea",
        "host": "vpn851811740.opengw.net",
        "port": 995,
        "username": "vpn",
        "password": "vpn",
        "is_new": false
    },
    {
        "id": "vpn169804096.opengw.net:1738",
        "name": "Unknown 14",
        "country": "Unknown",
        "host": "vpn169804096.opengw.net",
        "port": 1738,
        "username": "vpn",
        "password": "vpn",
        "is_new": false
    },
    {
        "id": "vpn854514241.opengw.net:995",
        "name": "South Korea 96",
        "country": "South Korea",
        "host": "vpn854514241.opengw.net",
        "port": 995,
        "username": "vpn",
        "password": "vpn",
        "is_new": false
    },
    {
        "id": "n26.opengw.net:1194",
        "name": "Japan 287",
        "country": "Japan",
        "host": "n26.opengw.net",
        "port": 1194,
        "username": "vpn",
        "password": "vpn",
        "is_new": false
    },
    {
        "id": "vpn937509069.opengw.net:995",
        "name": "South Korea 2",
        "country": "South Korea",
        "host": "vpn937509069.opengw.net",
        "port": 995,
        "username": "vpn",
        "password": "vpn",
        "is_new": false
    },
    {
        "id": "vpn592353452.opengw.net:1406",
        "name": "Japan 123",
        "country": "Japan",
        "host": "vpn592353452.opengw.net",
        "port": 1406,
        "username": "vpn",
        "password": "vpn",
        "is_new": false
    },
    {
        "id": "vpn483269236.opengw.net:1748",
        "name": "Japan 66",
        "country": "Japan",
        "host": "vpn483269236.opengw.net",
        "port": 1748,
        "username": "vpn",
        "password": "vpn",
        "is_new": false
    },
    {
        "id": "vpn456295025.opengw.net:1411",
        "name": "Japan 134",
        "country": "Japan",
        "host": "vpn456295025.opengw.net",
        "port": 1411,
        "username": "vpn",
        "password": "vpn",
        "is_new": false
    },
    {
        "id": "vpn922577537.opengw.net:1896",
        "name": "South Korea 388",
        "country": "South Korea",
        "host": "vpn922577537.opengw.net",
        "port": 1896,
        "username": "vpn",
        "password": "vpn",
        "is_new": false
    },
    {
        "id": "vpn435394266.opengw.net:1495",
        "name": "Japan 699",
        "country": "Japan",
        "host": "vpn435394266.opengw.net",
        "port": 1495,
        "username": "vpn",
        "password": "vpn",
        "is_new": false
    },
    {
        "id": "vpn461172806.opengw.net:995",
        "name": "South Korea 694",
        "country": "South Korea",
        "host": "vpn461172806.opengw.net",
        "port": 995,
        "username": "vpn",
        "password": "vpn",
        "is_new": false
    },
    {
        "id": "vpn954254224.opengw.net:1590",
        "name": "Russia 75",
        "country": "Russia",
        "host": "vpn954254224.opengw.net",
        "port": 1590,
        "username": "vpn",
        "password": "vpn",
        "is_new": false
    },
    {
        "id": "vpn683539447.opengw.net:1549",
        "name": "Japan 332",
        "country": "Japan",
        "host": "vpn683539447.opengw.net",
        "port": 1549,
        "username": "vpn",
        "password": "vpn",
        "is_new": false
    },
    {
        "id": "vpn349283646.opengw.net:1800",
        "name": "Japan 881",
        "country": "Japan",
        "host": "vpn349283646.opengw.net",
        "port": 1800,
        "username": "vpn",
        "password": "vpn",
        "is_new": false
    },
    {
        "id": "vpn294714738.opengw.net:1425",
        "name": "Japan 282",
        "country": "Japan",
        "host": "vpn294714738.opengw.net",
        "port": 1425,
        "username": "vpn",
        "password": "vpn",
        "is_new": false
    },
    {
        "id": "vpn398736484.opengw.net:1723",
        "name": "Unknown 133",
        "country": "Unknown",
        "host": "vpn398736484.opengw.net",
        "port": 1723,
        "username": "vpn",
        "password": "vpn",
        "is_new": false
    },
    {
        "id": "vpn641490835.opengw.net:1345",
        "name": "Japan 203",
        "country": "Japan",
        "host": "vpn641490835.opengw.net",
        "port": 1345,
        "username": "vpn",
        "password": "vpn",
        "is_new": false
    },
    {
        "id": "vpn701215762.opengw.net:1469",
        "name": "Thailand 18",
        "country": "Thailand",
        "host": "vpn701215762.opengw.net",
        "port": 1469,
        "username": "vpn",
        "password": "vpn",
        "is_new": false
    },
    {
        "id": "vpn486404568.opengw.net:1595",
        "name": "South Korea 619",
        "country": "South Korea",
        "host": "vpn486404568.opengw.net",
        "port": 1595,
        "username": "vpn",
        "password": "vpn",
        "is_new": false
    },
    {
        "id": "vpn461910067.opengw.net:995",
        "name": "South Korea 895",
        "country": "South Korea",
        "host": "vpn461910067.opengw.net",
        "port": 995,
        "username": "vpn",
        "password": "vpn",
        "is_new": false
    },
    {
        "id": "vpn110472687.opengw.net:1418",
        "name": "Japan 467",
        "country": "Japan",
        "host": "vpn110472687.opengw.net",
        "port": 1418,
        "username": "vpn",
        "password": "vpn",
        "is_new": false
    },
    {
        "id": "vpn974535826.opengw.net:1570",
        "name": "United States 12",
        "country": "United States",
        "host": "vpn974535826.opengw.net",
        "port": 1570,
        "username": "vpn",
        "password": "vpn",
        "is_new": false
    },
    {
        "id": "vpn266441259.opengw.net:1777",
        "name": "Japan 865",
        "country": "Japan",
        "host": "vpn266441259.opengw.net",
        "port": 1777,
        "username": "vpn",
        "password": "vpn",
        "is_new": false
    },
    {
        "id": "vpn273131016.opengw.net:1602",
        "name": "Japan 776",
        "country": "Japan",
        "host": "vpn273131016.opengw.net",
        "port": 1602,
        "username": "vpn",
        "password": "vpn",
        "is_new": false
    },
    {
        "id": "vpn571931610.opengw.net:1909",
        "name": "Japan 132",
        "country": "Japan",
        "host": "vpn571931610.opengw.net",
        "port": 1909,
        "username": "vpn",
        "password": "vpn",
        "is_new": false
    },
    {
        "id": "vpn196331168.opengw.net:1903",
        "name": "South Korea 362",
        "country": "South Korea",
        "host": "vpn196331168.opengw.net",
        "port": 1903,
        "username": "vpn",
        "password": "vpn",
        "is_new": false
    },
    {
        "id": "vpn339723621.opengw.net:995",
        "name": "South Korea 513",
        "country": "South Korea",
        "host": "vpn339723621.opengw.net",
        "port": 995,
        "username": "vpn",
        "password": "vpn",
        "is_new": false
    },
    {
        "id": "vpn966869813.opengw.net:1297",
        "name": "South Korea 167",
        "country": "South Korea",
        "host": "vpn966869813.opengw.net",
        "port": 1297,
        "username": "vpn",
        "password": "vpn",
        "is_new": false
    },
    {
        "id": "vpn283661088.opengw.net:1932",
        "name": "South Korea 93",
        "country": "South Korea",
        "host": "vpn283661088.opengw.net",
        "port": 1932,
        "username": "vpn",
        "password": "vpn",
        "is_new": false
    },
    {
        "id": "vpn278330694.opengw.net:1999",
        "name": "South Korea 170",
        "country": "South Korea",
        "host": "vpn278330694.opengw.net",
        "port": 1999,
        "username": "vpn",
        "password": "vpn",
        "is_new": false
    },
    {
        "id": "vpn133101722.opengw.net:995",
        "name": "South Korea 279",
        "country": "South Korea",
        "host": "vpn133101722.opengw.net",
        "port": 995,
        "username": "vpn",
        "password": "vpn",
        "is_new": false
    },
    {
        "id": "vpn171221818.opengw.net:1350",
        "name": "Japan 835",
        "country": "Japan",
        "host": "vpn171221818.opengw.net",
        "port": 1350,
        "username": "vpn",
        "password": "vpn",
        "is_new": false
    }
]