[
    {
        "id": "vpn885505990.opengw.net:1816",
        "name": "Japan 1991",
        "country": "Japan",
        "host": "vpn885505990.opengw.net",
        "port": 1816,
        "username": "vpn",
        "password": "vpn",
        "is_new": true
    },
    {
        "id": "vpn928700309.opengw.net:1894",
        "name": "Japan 1992",
        "country": "Japan",
        "host": "vpn928700309.opengw.net",
        "port": 1894,
        "username": "vpn",
        "password": "vpn",
        "is_new": true
    },
    {
        "id": "vpn935721051.opengw.net:1587",
        "name": "United Kingdom 9",
        "country": "United Kingdom",
        "host": "vpn935721051.opengw.net",
        "port": 1587,
        "username": "vpn",
        "password": "vpn",
        "is_new": true
    },
    {
        "id": "vpn436028708.opengw.net:1512",
        "name": "Vietnam 121",
        "country": "Vietnam",
        "host": "vpn436028708.opengw.net",
        "port": 1512,
        "username": "vpn",
        "password": "vpn",
        "is_new": true
    },
    {
        "id": "vpn194630455.opengw.net:995",
        "name": "South Korea 2117",
        "country": "South Korea",
        "host": "vpn194630455.opengw.net",
        "port": 995,
        "username": "vpn",
        "password": "vpn",
        "is_new": true
    },
    {
        "id": "vpn639044982.opengw.net:995",
        "name": "South Korea 2118",
        "country": "South Korea",
        "host": "vpn639044982.opengw.net",
        "port": 995,
        "username": "vpn",
        "password": "vpn",
        "is_new": true
    },
    {
        "id": "vpn955128001.opengw.net:1242",
        "name": "South Korea 2119",
        "country": "South Korea",
        "host": "vpn955128001.opengw.net",
        "port": 1242,
        "username": "vpn",
        "password": "vpn",
        "is_new": true
    },
    {
        "id": "vpn598634451.opengw.net:1902",
        "name": "Russia 419",
        "country": "Russia",
        "host": "vpn598634451.opengw.net",
        "port": 1902,
        "username": "vpn",
        "password": "vpn",
        "is_new": true
    },
    {
        "id": "vpn614156922.opengw.net:1526",
        "name": "United States 187",
        "country": "United States",
        "host": "vpn614156922.opengw.net",
        "port": 1526,
        "username": "vpn",
        "password": "vpn",
        "is_new": false
    },
    {
        "id": "vpn577708459.opengw.net:1651",
        "name": "Thailand 66",
        "country": "Thailand",
        "host": "vpn577708459.opengw.net",
        "port": 1651,
        "username": "vpn",
        "password": "vpn",
        "is_new": false
    },
    {
        "id": "vpn975550277.opengw.net:1514",
        "name": "Japan 365",
        "country": "Japan",
        "host": "vpn975550277.opengw.net",
        "port": 1514,
        "username": "vpn",
        "password": "vpn",
        "is_new": false
    },
    {
        "id": "vpn942772599.opengw.net:995",
        "name": "Unknown 209",
        "country": "Unknown",
        "host": "vpn942772599.opengw.net",
        "port": 995,
        "username": "vpn",
        "password": "vpn",
        "is_new": false
    },
    {
        "id": "vpn555964923.opengw.net:1782",
        "name": "South Korea 1410",
        "country": "South Korea",
        "host": "vpn555964923.opengw.net",
        "port": 1782,
        "username": "vpn",
        "password": "vpn",
        "is_new": false
    },
    {
        "id": "vpn486744122.opengw.net:1598",
        "name": "South Korea 1221",
        "country": "South Korea",
        "host": "vpn486744122.opengw.net",
        "port": 1598,
        "username": "vpn",
        "password": "vpn",
        "is_new": false
    },
    {
        "id": "vpn270057496.opengw.net:995",
        "name": "South Korea 1241",
        "country": "South Korea",
        "host": "vpn270057496.opengw.net",
        "port": 995,
        "username": "vpn",
        "password": "vpn",
        "is_new": false
    },
    {
        "id": "vpn787943520.opengw.net:1643",
        "name": "Japan 1822",
        "country": "Japan",
        "host": "vpn787943520.opengw.net",
        "port": 1643,
        "username": "vpn",
        "password": "vpn",
        "is_new": false
    },
    {
        "id": "vpn488412214.opengw.net:1806",
        "name": "United States 19",
        "country": "United States",
        "host": "vpn488412214.opengw.net",
        "port": 1806,
        "username": "vpn",
        "password": "vpn",
        "is_new": false
    },
    {
        "id": "vpn906340167.opengw.net:1701",
        "name": "South Korea 1340",
        "country": "South Korea",
        "host": "vpn906340167.opengw.net",
        "port": 1701,
        "username": "vpn",
        "password": "vpn",
        "is_new": false
    },
    {
        "id": "n26.opengw.net:1194",
        "name": "Japan 287",
        "country": "Japan",
        "host": "n26.opengw.net",
        "port": 1194,
        "username": "vpn",
        "password": "vpn",
        "is_new": false
    },
    {
        "id": "vpn252995723.opengw.net:1808",
        "name": "Japan 993",
        "country": "Japan",
        "host": "vpn252995723.opengw.net",
        "port": 1808,
        "username": "vpn",
        "password": "vpn",
        "is_new": false
    },
    {
        "id": "vpn259839631.opengw.net:1624",
        "name": "Japan 908",
        "country": "Japan",
        "host": "vpn259839631.opengw.net",
        "port": 1624,
        "username": "vpn",
        "password": "vpn",
        "is_new": false
    },
    {
        "id": "vpn540904816.opengw.net:1812",
        "name": "Japan 841",
        "country": "Japan",
        "host": "vpn540904816.opengw.net",
        "port": 1812,
        "username": "vpn",
        "password": "vpn",
        "is_new": false
    },
    {
        "id": "vpn256739757.opengw.net:1882",
        "name": "South Korea 1551",
        "country": "South Korea",
        "host": "vpn256739757.opengw.net",
        "port": 1882,
        "username": "vpn",
        "password": "vpn",
        "is_new": false
    },
    {
        "id": "vpn457253712.opengw.net:1589",
        "name": "South Korea 2028",
        "country": "South Korea",
        "host": "vpn457253712.opengw.net",
        "port": 1589,
        "username": "vpn",
        "password": "vpn",
        "is_new": false
    },
    {
        "id": "vpn782202640.opengw.net:1456",
        "name": "South Korea 815",
        "country": "South Korea",
        "host": "vpn782202640.opengw.net",
        "port": 1456,
        "username": "vpn",
        "password": "vpn",
        "is_new": false
    },
    {
        "id": "vpn892429087.opengw.net:1336",
        "name": "South Korea 496",
        "country": "South Korea",
        "host": "vpn892429087.opengw.net",
        "port": 1336,
        "username": "vpn",
        "password": "vpn",
        "is_new": false
    },
    {
        "id": "vpn986363336.opengw.net:1777",
        "name": "Japan 1890",
        "country": "Japan",
        "host": "vpn986363336.opengw.net",
        "port": 1777,
        "username": "vpn",
        "password": "vpn",
        "is_new": false
    },
    {
        "id": "vpn233431174.opengw.net:1986",
        "name": "South Korea 2038",
        "country": "South Korea",
        "host": "vpn233431174.opengw.net",
        "port": 1986,
        "username": "vpn",
        "password": "vpn",
        "is_new": false
    },
    {
        "id": "vpn622670753.opengw.net:1865",
        "name": "Japan 1033",
        "country": "Japan",
        "host": "vpn622670753.opengw.net",
        "port": 1865,
        "username": "vpn",
        "password": "vpn",
        "is_new": false
    },
    {
        "id": "vpn844508033.opengw.net:1558",
        "name": "Japan 567",
        "country": "Japan",
        "host": "vpn844508033.opengw.net",
        "port": 1558,
        "username": "vpn",
        "password": "vpn",
        "is_new": false
    },
    {
        "id": "vpn654677818.opengw.net:1724",
        "name": "South Korea 1203",
        "country": "South Korea",
        "host": "vpn654677818.opengw.net",
        "port": 1724,
        "username": "vpn",
        "password": "vpn",
        "is_new": false
    },
    {
        "id": "vpn832620619.opengw.net:1749",
        "name": "Japan 1711",
        "country": "Japan",
        "host": "vpn832620619.opengw.net",
        "port": 1749,
        "username": "vpn",
        "password": "vpn",
        "is_new": false
    },
    {
        "id": "vpn937444270.opengw.net:1927",
        "name": "Vietnam 90",
        "country": "Vietnam",
        "host": "vpn937444270.opengw.net",
        "port": 1927,
        "username": "vpn",
        "password": "vpn",
        "is_new": false
    },
    {
        "id": "vpn783293517.opengw.net:1544",
        "name": "Japan 314",
        "country": "Japan",
        "host": "vpn783293517.opengw.net",
        "port": 1544,
        "username": "vpn",
        "password": "vpn",
        "is_new": false
    },
    {
        "id": "vpn722645980.opengw.net:1847",
        "name": "Japan 992",
        "country": "Japan",
        "host": "vpn722645980.opengw.net",
        "port": 1847,
        "username": "vpn",
        "password": "vpn",
        "is_new": false
    },
    {
        "id": "vpn941975760.opengw.net:1710",
        "name": "Unknown 146",
        "country": "Unknown",
        "host": "vpn941975760.opengw.net",
        "port": 1710,
        "username": "vpn",
        "password": "vpn",
        "is_new": false
    },
    {
        "id": "vpn827317201.opengw.net:1641",
        "name": "Japan 953",
        "country": "Japan",
        "host": "vpn827317201.opengw.net",
        "port": 1641,
        "username": "vpn",
        "password": "vpn",
        "is_new": false
    },
    {
        "id": "vpn969228228.opengw.net:1721",
        "name": "Japan 316",
        "country": "Japan",
        "host": "vpn969228228.opengw.net",
        "port": 1721,
        "username": "vpn",
        "password": "vpn",
        "is_new": false
    },
    {
        "id": "vpn136044741.opengw.net:1306",
        "name": "Japan 27",
        "country": "Japan",
        "host": "vpn136044741.opengw.net",
        "port": 1306,
        "username": "vpn",
        "password": "vpn",
        "is_new": false
    },
    {
        "id": "vpn258563631.opengw.net:1423",
        "name": "Japan 695",
        "country": "Japan",
        "host": "vpn258563631.opengw.net",
        "port": 1423,
        "username": "vpn",
        "password": "vpn",
        "is_new": false
    },
    {
        "id": "vpn748512588.opengw.net:1534",
        "name": "Japan 951",
        "country": "Japan",
        "host": "vpn748512588.opengw.net",
        "port": 1534,
        "username": "vpn",
        "password": "vpn",
        "is_new": false
    },
    {
        "id": "vpn228863671.opengw.net:1247",
        "name": "Thailand 17",
        "country": "Thailand",
        "host": "vpn228863671.opengw.net",
        "port": 1247,
        "username": "vpn",
        "password": "vpn",
        "is_new": false
    },
    {
        "id": "vpn710141337.opengw.net:1289",
        "name": "Japan 1584",
        "country": "Japan",
        "host": "vpn710141337.opengw.net",
        "port": 1289,
        "username": "vpn",
        "password": "vpn",
        "is_new": false
    },
    {
        "id": "vpn846477375.opengw.net:1657",
        "name": "South Korea 130",
        "country": "South Korea",
        "host": "vpn846477375.opengw.net",
        "port": 1657,
        "username": "vpn",
        "password": "vpn",
        "is_new": false
    },
    {
        "id": "vpn283661088.opengw.net:1932",
        "name": "South Korea 93",
        "country": "South Korea",
        "host": "vpn283661088.opengw.net",
        "port": 1932,
        "username": "vpn",
        "password": "vpn",
        "is_new": false
    },
    {
        "id": "vpn475780323.opengw.net:1763",
        "name": "Japan 718",
        "country": "Japan",
        "host": "vpn475780323.opengw.net",
        "port": 1763,
        "username": "vpn",
        "password": "vpn",
        "is_new": false
    },
    {
        "id": "vpn427539242.opengw.net:1343",
        "name": "Japan 1345",
        "country": "Japan",
        "host": "vpn427539242.opengw.net",
        "port": 1343,
        "username": "vpn",
        "password": "vpn",
        "is_new": false
    },
    {
        "id": "vpn906428200.opengw.net:1637",
        "name": "Japan 670",
        "country": "Japan",
        "host": "vpn906428200.opengw.net",
        "port": 1637,
        "username": "vpn",
        "password": "vpn",
        "is_new": false
    },
    {
        "id": "vpn196305880.opengw.net:1205",
        "name": "Japan 1723",
        "country": "Japan",
        "host": "vpn196305880.opengw.net",
        "port": 1205,
        "username": "vpn",
        "password": "vpn",
        "is_new": false
    },
    {
        "id": "vpn509369109.opengw.net:1602",
        "name": "Japan 702",
        "country": "Japan",
        "host": "vpn509369109.opengw.net",
        "port": 1602,
        "username": "vpn",
        "password": "vpn",
        "is_new": false
    },
    {
        "id": "vpn492686662.opengw.net:1591",
        "name": "Japan 1333",
        "country": "Japan",
        "host": "vpn492686662.opengw.net",
        "port": 1591,
        "username": "vpn",
        "password": "vpn",
        "is_new": false
    },
    {
        "id": "vpn276074191.opengw.net:1816",
        "name": "France 19",
        "country": "France",
        "host": "vpn276074191.opengw.net",
        "port": 1816,
        "username": "vpn",
        "password": "vpn",
        "is_new": false
    },
    {
        "id": "vpn214016347.opengw.net:995",
        "name": "South Korea 850",
        "country": "South Korea",
        "host": "vpn214016347.opengw.net",
        "port": 995,
        "username": "vpn",
        "password": "vpn",
        "is_new": false
    },
    {
        "id": "vpn421506563.opengw.net:1679",
        "name": "Japan 1495",
        "country": "Japan",
        "host": "vpn421506563.opengw.net",
        "port": 1679,
        "username": "vpn",
        "password": "vpn",
        "is_new": false
    },
    {
        "id": "vpn650145616.opengw.net:1316",
        "name": "Japan 1490",
        "country": "Japan",
        "host": "vpn650145616.opengw.net",
        "port": 1316,
        "username": "vpn",
        "password": "vpn",
        "is_new": false
    },
    {
        "id": "vpn906940084.opengw.net:1711",
        "name": "Japan 1269",
        "country": "Japan",
        "host": "vpn906940084.opengw.net",
        "port": 1711,
        "username": "vpn",
        "password": "vpn",
        "is_new": false
    },
    {
        "id": "vpn935888099.opengw.net:1393",
        "name": "Japan 1196",
        "country": "Japan",
        "host": "vpn935888099.opengw.net",
        "port": 1393,
        "username": "vpn",
        "password": "vpn",
        "is_new": false
    },
    {
        "id": "vpn877776361.opengw.net:1235",
        "name": "Japan 1420",
        "country": "Japan",
        "host": "vpn877776361.opengw.net",
        "port": 1235,
        "username": "vpn",
        "password": "vpn",
        "is_new": false
    },
    {
        "id": "vpn455812415.opengw.net:1673",
        "name": "Japan 1397",
        "country": "Japan",
        "host": "vpn455812415.opengw.net",
        "port": 1673,
        "username": "vpn",
        "password": "vpn",
        "is_new": false
    },
    {
        "id": "vpn651589378.opengw.net:1490",
        "name": "Japan 133",
        "country": "Japan",
        "host": "vpn651589378.opengw.net",
        "port": 1490,
        "username": "vpn",
        "password": "vpn",
        "is_new": false
    },
    {
        "id": "vpn740752971.opengw.net:1782",
        "name": "South Korea 104",
        "country": "South Korea",
        "host": "vpn740752971.opengw.net",
        "port": 1782,
        "username": "vpn",
        "password": "vpn",
        "is_new": false
    },
    {
        "id": "vpn606229899.opengw.net:995",
        "name": "South Korea 1087",
        "country": "South Korea",
        "host": "vpn606229899.opengw.net",
        "port": 995,
        "username": "vpn",
        "password": "vpn",
        "is_new": false
    },
    {
        "id": "vpn281927743.opengw.net:1314",
        "name": "Russia 288",
        "country": "Russia",
        "host": "vpn281927743.opengw.net",
        "port": 1314,
        "username": "vpn",
        "password": "vpn",
        "is_new": false
    },
    {
        "id": "vpn633347197.opengw.net:995",
        "name": "South Korea 323",
        "country": "South Korea",
        "host": "vpn633347197.opengw.net",
        "port": 995,
        "username": "vpn",
        "password": "vpn",
        "is_new": false
    },
    {
        "id": "vpn558032864.opengw.net:995",
        "name": "South Korea 1356",
        "country": "South Korea",
        "host": "vpn558032864.opengw.net",
        "port": 995,
        "username": "vpn",
        "password": "vpn",
        "is_new": false
    },
    {
        "id": "vpn607876486.opengw.net:995",
        "name": "South Korea 1283",
        "country": "South Korea",
        "host": "vpn607876486.opengw.net",
        "port": 995,
        "username": "vpn",
        "password": "vpn",
        "is_new": false
    },
    {
        "id": "vpn495744622.opengw.net:995",
        "name": "South Korea 2051",
        "country": "South Korea",
        "host": "vpn495744622.opengw.net",
        "port": 995,
        "username": "vpn",
        "password": "vpn",
        "is_new": false
    },
    {
        "id": "vpn383069700.opengw.net:1795",
        "name": "Russia 35",
        "country": "Russia",
        "host": "vpn383069700.opengw.net",
        "port": 1795,
        "username": "vpn",
        "password": "vpn",
        "is_new": false
    },
    {
        "id": "vpn670513202.opengw.net:1718",
        "name": "United States 23",
        "country": "United States",
        "host": "vpn670513202.opengw.net",
        "port": 1718,
        "username": "vpn",
        "password": "vpn",
        "is_new": false
    },
    {
        "id": "vpn554495146.opengw.net:1823",
        "name": "South Korea 1216",
        "country": "South Korea",
        "host": "vpn554495146.opengw.net",
        "port": 1823,
        "username": "vpn",
        "password": "vpn",
        "is_new": false
    },
    {
        "id": "vpn440153554.opengw.net:1323",
        "name": "Russia 381",
        "country": "Russia",
        "host": "vpn440153554.opengw.net",
        "port": 1323,
        "username": "vpn",
        "password": "vpn",
        "is_new": false
    },
    {
        "id": "vpn343892309.opengw.net:1822",
        "name": "Russia 410",
        "country": "Russia",
        "host": "vpn343892309.opengw.net",
        "port": 1822,
        "username": "vpn",
        "password": "vpn",
        "is_new": false
    },
    {
        "id": "vpn902198461.opengw.net:1919",
        "name": "South Korea 1226",
        "country": "South Korea",
        "host": "vpn902198461.opengw.net",
        "port": 1919,
        "username": "vpn",
        "password": "vpn",
        "is_new": false
    }
]